Metadata-Version: 1.0
Name: meson-check
Version: 0.1.0
Summary: Check module for Meson build system
Home-page: https://snai.pe/git/meson-check
Author: Snaipe
Author-email: me@snai.pe
License: Apache v2
Platform: UNKNOWN
